{
	"type": "invoice",
	"prefix":{
		"id": "invoice1",
		"fname": "InfotechAS.pdf",
		"name": "InfotechAS",
		"keywords": [
				"InfotechAS",
				"faktura@infotech.no"
		]
	},
	"info": {
		"InvoiceDetails": [
			{
				"meaning": "InvoiceNumber",
				"keywords": [
					"Fakturanummer",
					"faktura nr."
				],
				"orientation": "left",
				"max_len": 5
			},
			{
				"meaning": "InvoiceIssueDate",
				"keywords": [
					"Fakturadato"
				],
				"orientation": "left",
				"max_len": 8
			},
			{
				"meaning": "InvoiceDueDate",
				"keywords": [
					"Forfallsdato", "Forfallsdata"
				],
				"orientation": "left",
				"max_len": 8
			},
			{
				"meaning": "TransactionID",
				"keywords": [
					""
				],
				"orientation": "left",
				"max_len": 5
			},
			{
				"meaning": "InvoiceReference",
				"keywords": [
					"Deres ref."
				],
				"orientation": "left",
				"max_len": 10
			},
			{
				"meaning": "Free Text",
				"keywords": [
					"Deres ref."
				],
				"orientation": "ext_under",
				"max_len": 10
			}
		],
		"InvoiceLines": {
			"type": "list",
			"orientation": "under",
			"components": [
				{
					"meaning": "LineID",
					"keywords": [
						""
					]
				},
				{
					"meaning" : "Quantity",
					"keywords": [
							"Ant."
						]
				},
				{
					"meaning": "Unit",
					"keywords": [
						"Enhet"
					]
				},
				{
					"meaning": "Description",
					"keywords": [
						"Beskrivelse"
					]
				},
				{
					"meaning": "Price",
					"keywords": [
						""
					]
				},
				{
					"meaning": "TotalLineAmount",
					"keywords": [
						"Beløp", "Belop", "Belep"
					]
				}
			]
		},
		"TotalTAXs": {
			"type": "list",
			"orientation": "left",
			"components":[
				{
					"meaning": "25%",
					"keywords": [
						"+25% MVA"
					]
				},
				{
					"meaning": "15%",
					"keywords": [
						""
					]
				},
				{
					"meaning": "10%",
					"keywords": [
						""
					]
				}
			]
		},
		"Totals": {
			"type": "list",
			"orientation": "left",
			"components": [
				{
					"meaning": "TotalInclusiveTAX",
					"keywords": [
						"Sum NOK"
					]
				}
			]
		}
	}
}